densefog/__init__.py
densefog/bootstrap.py
densefog/cache.py
densefog/config.py
densefog/db.py
densefog/error.py
densefog/logger.py
densefog/version.py
densefog/common/__init__.py
densefog/common/cliutils.py
densefog/common/db.py
densefog/common/jsonable.py
densefog/common/local.py
densefog/common/model.py
densefog/common/rediscache.py
densefog/common/request.py
densefog/common/service.py
densefog/common/shortuuid.py
densefog/common/utils.py
densefog/common/waiter.py
densefog/model/__init__.py
densefog/model/base.py
densefog/model/filters.py
densefog/model/job/__init__.py
densefog/model/job/job.py
densefog/model/journal/__init__.py
densefog/model/journal/operation.py
densefog/server/__init__.py
densefog/server/api.py
densefog/server/worker.py
densefog/web/__init__.py
densefog/web/grand.py
densefog/web/guard.py
densefog/web/middleware.py
densefog/web/stat.py
densefog-0.0.1.dev10.dist-info/AUTHORS
densefog-0.0.1.dev10.dist-info/METADATA
densefog-0.0.1.dev10.dist-info/WHEEL
densefog-0.0.1.dev10.dist-info/pbr.json
densefog-0.0.1.dev10.dist-info/top_level.txt
densefog-0.0.1.dev10.dist-info/RECORD
