Metadata-Version: 2.1
Name: densefog
Version: 0.0.1.dev10
License-File: AUTHORS
Requires-Dist: oslo.serialization
Requires-Dist: oslo.config
Requires-Dist: oslo.utils
Requires-Dist: six
Requires-Dist: gevent
Requires-Dist: Flask
Requires-Dist: SQLAlchemy
Requires-Dist: redis
Requires-Dist: jsonschema
Requires-Dist: PyMySQL
